CHANGELOG.rst
LICENSE.txt
MANIFEST.in
README.rst
TODO.txt
VERSION.txt
setup.cfg
setup.py
test-requirements.txt
iniherit/__init__.py
iniherit/cli.py
iniherit/interpolation.py
iniherit/mixin.py
iniherit/parser.py
iniherit/test.py
iniherit/test_cli.py
iniherit.egg-info/PKG-INFO
iniherit.egg-info/SOURCES.txt
iniherit.egg-info/dependency_links.txt
iniherit.egg-info/entry_points.txt
iniherit.egg-info/requires.txt
iniherit.egg-info/top_level.txt
iniherit.egg-info/zip-safe