Metadata-Version: 1.1
Name: iniherit
Version: 0.3.5
Summary: A ConfigParser subclass with file-specified inheritance.
Home-page: http://github.com/cadithealth/iniherit
Author: Philip J Grabner, Cadit Health Inc
Author-email: oss@cadit.com
License: MIT (http://opensource.org/licenses/MIT)
Keywords: INI inheritance configparser mixin
Platform: UNKNOWN
Classifier: Development Status :: 5 - Production/Stable
Classifier: Intended Audience :: Developers
Classifier: Programming Language :: Python
Classifier: Operating System :: OS Independent
Classifier: Natural Language :: English
Classifier: License :: OSI Approved :: MIT License
Classifier: License :: Public Domain
